scripts/allorgs_covplot.py
scripts/parse_bact_fung_reads.py
scripts/treemap.R
virmet/__init__.py
virmet/__main__.py
virmet/cli.py
virmet/common.py
virmet/covplot.R
virmet/covplot.py
virmet/fetch.py
virmet/index.py
virmet/tidytable.py
virmet/update.py
virmet/wolfpack.py
virmet-2.0.1.dist-info/METADATA
virmet-2.0.1.dist-info/WHEEL
virmet-2.0.1.dist-info/entry_points.txt
virmet-2.0.1.dist-info/top_level.txt
virmet-2.0.1.dist-info/RECORD
