Metadata-Version: 2.4
Name: virmet
Version: 2.0.1
Summary: Viral metagenomics in clinical applications
Author: Osvaldo Zagordi
Maintainer-email: Judith Bergadà <bergada.judith@virology.uzh.ch>
License: MIT
Project-URL: Documentation, https://medvir.github.io/VirMet/
Project-URL: Source, http://github.com/medvir/VirMet
Project-URL: Tracker, http://github.com/medvir/VirMet/issues
Classifier: Development Status :: 5 - Production/Stable
Classifier: Intended Audience :: Developers
Classifier: Topic :: Scientific/Engineering :: Bio-Informatics
Classifier: Topic :: Scientific/Engineering :: Medical Science Apps.
Classifier: License :: OSI Approved :: MIT License
Classifier: Programming Language :: Python :: 3 :: Only
Classifier: Programming Language :: Python :: 3.8
Classifier: Programming Language :: Python :: 3.9
Classifier: Programming Language :: Python :: 3.10
Classifier: Programming Language :: Python :: 3.11
Classifier: Programming Language :: Python :: 3.12
Requires-Python: >=3.9
Requires-Dist: pandas
Requires-Dist: Bio
Requires-Dist: numpy
Provides-Extra: dev
Requires-Dist: pytest; extra == "dev"
Requires-Dist: pytest-cov; extra == "dev"
Requires-Dist: ruff; extra == "dev"
Requires-Dist: bandit; extra == "dev"
